pkl/__init__.py
pkl/atomic.py
pkl/decode_map.py
pkl/decode_primitives.py
pkl/decode_slice.py
pkl/decode_struct.py
pkl/decoder.py
pkl/errors.py
pkl/evaluator.py
pkl/evaluator_exec.py
pkl/evaluator_manager.py
pkl/evaluator_manager_exec.py
pkl/evaluator_options.py
pkl/fs_reader.py
pkl/internal/debug.py
pkl/internal/msgapi/code.py
pkl/internal/msgapi/incoming.py
pkl/internal/msgapi/outgoing.py
pkl/logger.py
pkl/module_source.py
pkl/project.py
pkl/reader.py
pkl/schema.py
pkl/unmarshal.py
pkl/values.py
python_pkl-0.1.3.dist-info/LICENCE.txt
python_pkl-0.1.3.dist-info/METADATA
python_pkl-0.1.3.dist-info/WHEEL
python_pkl-0.1.3.dist-info/RECORD
