Metadata-Version: 2.1
Name: python-pkl
Version: 0.1.3
Summary: Python library to work with Apple's PKL files
Author: Vithor Jaeger
Author-email: vaphes@gmail.com
Requires-Python: >=3.12,<4.0
Classifier: Programming Language :: Python :: 3
Classifier: Programming Language :: Python :: 3.12
Project-URL: Bug Tracker, https://github.com/vaphes/python-pkl/issues
Project-URL: Homepage, https://github.com/vaphes/python-pkl
Project-URL: Source, https://github.com/vaphes/python-pkl
